scapy/__init__.py
scapy/__version__.py
scapy/cli/__init__.py
scapy/cli/delpoy.py
scapy/cli/download.py
scapy/cli/settings.py
scapy/cli/utils.py
scapy/cli/generator/__init__.py
scapy/cli/generator/password.py
scapy/cli/generator/worker.py
scapy/cli/paths/__init__.py
scapy/cli/paths/certificates.py
scapy/cli/paths/configs.py
scapy/cli/paths/passwords.py
scapy/cli/paths/secrets.py
scapy/core/__init__.py
scapy/core/worker.py
scapy/data/worker.js
scapy_man-0.3.3.dist-info/LICENSE
scapy_man-0.3.3.dist-info/METADATA
scapy_man-0.3.3.dist-info/WHEEL
scapy_man-0.3.3.dist-info/entry_points.txt
scapy_man-0.3.3.dist-info/top_level.txt
scapy_man-0.3.3.dist-info/RECORD
