Metadata-Version: 2.1
Name: scapy-man
Version: 0.3.3
Summary: Step CA Manager using Python
Home-page: https://github.com/nikhiljohn10/scapy
Author: Nikhil John
Author-email: nikhiljohn1010@gmail.com
License: MIT
Keywords: step-ca,cloudflare-api,workers,certificate,cli
Platform: UNKNOWN
Classifier: Development Status :: 5 - Production/Stable
Classifier: Intended Audience :: Developers
Classifier: Topic :: Software Development :: Libraries :: Python Modules
Classifier: License :: OSI Approved :: MIT License
Classifier: Programming Language :: Python :: 3
Classifier: Programming Language :: Python :: 3.8
Classifier: Programming Language :: Python :: 3.9
License-File: LICENSE
Requires-Dist: cloudflare-api (>=2.0.4)
Requires-Dist: Click
Requires-Dist: click-completion
